pfFPGATools/Exceptions.py
pfFPGATools/__about__.py
pfFPGATools/__init__.py
pfFPGATools/utils.py
pfFPGATools/pfBuildCore/__main__.py
pfFPGATools/pfBuildCore/pfBuildCore.py
pfFPGATools/pfCloneCoreTemplate/__main__.py
pfFPGATools/pfCloneCoreTemplate/pfCloneCoreTemplate.py
pfFPGATools/pfConvertImage/__main__.py
pfFPGATools/pfConvertImage/pfConvertImage.py
pfFPGATools/pfInstallCore/__main__.py
pfFPGATools/pfInstallCore/pfInstallCore.py
pfFPGATools/pfQuartusEdit/__main__.py
pfFPGATools/pfQuartusEdit/pfQuartusEdit.py
pfFPGATools/pfReverseBitstream/__main__.py
pfFPGATools/pfReverseBitstream/pfReverseBitstream.py
pf_fpga_tools-0.0.9.dist-info/METADATA
pf_fpga_tools-0.0.9.dist-info/WHEEL
pf_fpga_tools-0.0.9.dist-info/entry_points.txt
pf_fpga_tools-0.0.9.dist-info/licenses/LICENSE
pf_fpga_tools-0.0.9.dist-info/RECORD
