Metadata-Version: 2.1
Name: pf-fpga-tools
Version: 0.0.9
Summary: A collection of tools for openFPGA projects
Project-URL: Homepage, https://didier.malenfant.net/ProjectFreedom/
Project-URL: Documentation, https://github.com/DidierMalenfant/pfFPGATools#readme
Project-URL: Bug Tracker, https://github.com/DidierMalenfant/pfFPGATools/issues
Project-URL: Source Code, https://github.com/DidierMalenfant/pfFPGATools
Author-email: Didier Malenfant <coding@malenfant.net>
License-Expression: GPL-3.0-or-later
License-File: LICENSE
Keywords: analoguepocket,fpga,openFPGA
Classifier: Development Status :: 5 - Production/Stable
Classifier: Programming Language :: Python
Classifier: Programming Language :: Python :: 3.10
Classifier: Programming Language :: Python :: Implementation :: CPython
Classifier: Programming Language :: Python :: Implementation :: PyPy
Requires-Python: >=3.10
Requires-Dist: pillow
Requires-Dist: tomli>=1.1.0; python_version < '3.11'
